extra/__init__.py
extra/Arducam-OV2640-Pico-Package/Arducam_OV2640.py
extra/Arducam-OV2640-Pico-Package/OV2640_reg.py
extra/Arducam-OV2640-Pico-Package/Pico_imager.py
extra/Arducam-OV2640-Pico-Package/code.py
extra/adafruit_io_sdl_demo/adafruit_io_sdl_demo.py
extra/adafruit_io_sdl_demo/as7341_basic.py
extra/adafruit_io_sdl_demo/config.py
extra/adafruit_io_sdl_demo/main.py
extra/adafruit_io_sdl_demo/neopixel_as7341_basic.py
extra/adafruit_io_sdl_demo/neopixel_basic.py
extra/adafruit_io_sdl_demo/sample_secrets.py
extra/adafruit_io_sdl_demo/lib/as7341.py
extra/adafruit_io_sdl_demo/lib/as7341_sensor.py
extra/adafruit_io_sdl_demo/lib/as7341_smux_select.py
extra/adafruit_io_sdl_demo/lib/mqtt.py
extra/circuitpython_arducam/boot.py
extra/circuitpython_arducam/lib/ArduCAM_Mini_2MP_Plus_VideoStreaming.py
extra/circuitpython_arducam/lib/ArduCAM_Mini_5MP_Plus_VideoStreaming.py
extra/circuitpython_arducam/lib/Arducam.py
extra/circuitpython_arducam/lib/OV2640_reg.py
extra/circuitpython_arducam/lib/OV5642_reg.py
extra/circuitpython_mqtt_sdl_demo/code.py
extra/circuitpython_mqtt_sdl_demo/scripts/minimal.py
extra/circuitpython_mqtt_sdl_demo/scripts/minimal_2.py
extra/circuitpython_mqtt_sdl_demo/scripts/minimqtt_simpletest.py
extra/circuitpython_mqtt_sdl_demo/scripts/neopixel_as7341_basic.py
extra/circuitpython_mqtt_sdl_demo/scripts/onboard_led_basic.py
extra/circuitpython_mqtt_sdl_demo/scripts/server_reproducer.py
extra/circuitpython_sdl_demo/boot.py
extra/circuitpython_sdl_demo/circuitpy-2022-08-27.zip
extra/circuitpython_sdl_demo/code.py
extra/circuitpython_sdl_demo/scripts/as7341_basic.py
extra/circuitpython_sdl_demo/scripts/neopixel_as7341_basic.py
extra/circuitpython_sdl_demo/scripts/neopixel_basic.py
extra/micropython_sdl_demo/README.md
extra/micropython_sdl_demo/as7341_basic.py
extra/micropython_sdl_demo/main.py
extra/micropython_sdl_demo/microdot_basic.py
extra/micropython_sdl_demo/neopixel_as7341_basic.py
extra/micropython_sdl_demo/neopixel_basic.py
self_driving_lab_demo-0.8.12.dist-info/licenses/LICENSE.txt
self_driving_lab_demo-0.8.12.dist-info/METADATA
self_driving_lab_demo-0.8.12.dist-info/WHEEL
self_driving_lab_demo-0.8.12.dist-info/entry_points.txt
self_driving_lab_demo-0.8.12.dist-info/top_level.txt
self_driving_lab_demo-0.8.12.dist-info/RECORD
