Metadata-Version: 2.4
Name: self-driving-lab-demo
Version: 0.8.12
Summary: Software and instructions for setting up and running an autonomous (self-driving) laboratory optics demo using dimmable RGB LEDs, a 10-channel spectrometer, a microcontroller, and an adaptive design algorithm.
Home-page: https://github.com/sparks-baird/self-driving-lab-demo/
Author: sgbaird
Author-email: sterling.baird@utah.edu
License: MIT
Project-URL: Documentation, https://pyscaffold.org/
Platform: any
Classifier: Development Status :: 4 - Beta
Classifier: Programming Language :: Python
License-File: LICENSE.txt
Requires-Dist: importlib-metadata; python_version < "3.8"
Requires-Dist: numpy
Requires-Dist: pandas
Requires-Dist: tqdm
Requires-Dist: nbformat
Requires-Dist: kaleido
Requires-Dist: plotly
Requires-Dist: ipykernel
Requires-Dist: ipywidgets
Requires-Dist: cython>=0.29.24
Requires-Dist: scipy
Requires-Dist: scikit-learn
Requires-Dist: scikit-optimize
Requires-Dist: gpytorch
Requires-Dist: ax-platform<1
Requires-Dist: similaritymeasures
Requires-Dist: requests
Requires-Dist: pyserial
Requires-Dist: paho-mqtt
Requires-Dist: pymongo
Provides-Extra: dev
Requires-Dist: rshell; extra == "dev"
Requires-Dist: esptool; extra == "dev"
Provides-Extra: testing
Requires-Dist: setuptools; extra == "testing"
Requires-Dist: pytest; extra == "testing"
Requires-Dist: pytest-cov; extra == "testing"
Requires-Dist: pre-commit; extra == "testing"
Dynamic: license-file
